ont_fastq_deconcatenate/__init__.py
ont_fastq_deconcatenate/cli.py
ont_fastq_deconcatenate/fastq_fix.py
ont_fastq_deconcatenate-0.6.2.dist-info/LICENSE.md
ont_fastq_deconcatenate-0.6.2.dist-info/METADATA
ont_fastq_deconcatenate-0.6.2.dist-info/WHEEL
ont_fastq_deconcatenate-0.6.2.dist-info/entry_points.txt
ont_fastq_deconcatenate-0.6.2.dist-info/top_level.txt
ont_fastq_deconcatenate-0.6.2.dist-info/RECORD
