Metadata-Version: 2.1
Name: ont-fastq-deconcatenate
Version: 0.6.2
Summary: Fixes concatenated fastq records
Home-page: http://www.nanoporetech.com
Author: Oxford Nanopore Technologies, Limited
Author-email: unknown@unknown.com
License: UNKNOWN
Platform: UNKNOWN
Classifier: Development Status :: 4 - Beta
Classifier: Environment :: Console
Classifier: Intended Audience :: Developers
Classifier: Intended Audience :: Science/Research
Classifier: License :: OSI Approved :: Mozilla Public License 2.0 (MPL 2.0)
Classifier: Natural Language :: English
Classifier: Operating System :: POSIX :: Linux
Classifier: Programming Language :: C++
Classifier: Programming Language :: Python :: 3 :: Only
Classifier: Topic :: Scientific/Engineering :: Bio-Informatics
Requires-Dist: biopython (>=1.66)
Requires-Dist: progressbar33
